{
  "ports":{
    ":AN1":{"labels":{"ff":{"player":0,"name":"Gas Pedal"}}},
    ":AN2":{"labels":{"ff":{"player":0,"name":"Steering Wheel"}}},
    ":AN3":{"labels":{"ff":{"player":0,"name":"Brake Pedal"}}},
    ":PORTH":{
      "labels":{
        "8":{"player":0,"name":"Red Button"},
        "20":{"player":0,"name":"Green Button"}
      }
    },
    ":gearbox:CLUTCH":{"labels":{"1":{"player":1,"name":"Clutch Pedal"}}},
    ":gearbox:GEARBOX":{
      "labels":{
        "1":{"player":1,"name":"Gearbox Up"},
        "2":{"player":1,"name":"Gearbox Down"},
        "4":{"player":1,"name":"Gearbox Left"},
        "8":{"player":1,"name":"Gearbox Right"}
      }
    }
  }
}